MCSimPython/__init__.py
MCSimPython/utils.py
MCSimPython/control/__init__.py
MCSimPython/control/adaptiveFS.py
MCSimPython/control/backstepping.py
MCSimPython/control/basic.py
MCSimPython/guidance/__init__.py
MCSimPython/guidance/filter.py
MCSimPython/guidance/path_param.py
MCSimPython/observer/__init__.py
MCSimPython/observer/ekf.py
MCSimPython/observer/ltv_kf.py
MCSimPython/observer/nonlinobs.py
MCSimPython/simulator/__init__.py
MCSimPython/simulator/csad.py
MCSimPython/simulator/gunnerus.py
MCSimPython/simulator/thruster_dynamics.py
MCSimPython/simulator/vessel.py
MCSimPython/thrust_allocation/__init__.py
MCSimPython/thrust_allocation/allocation.py
MCSimPython/thrust_allocation/constraints.py
MCSimPython/thrust_allocation/thruster.py
MCSimPython/vessel_data/__init__.py
MCSimPython/vessel_data/CSAD/__init__.py
MCSimPython/vessel_data/CSAD/freqs.npy
MCSimPython/vessel_data/CSAD/headings.npy
MCSimPython/vessel_data/CSAD/thruster_data.py
MCSimPython/vessel_data/CSAD/vesselABC_json.json
MCSimPython/vessel_data/CSAD/vessel_json.json
MCSimPython/vessel_data/gunnerus/__init__.py
MCSimPython/vessel_data/gunnerus/gunnerusABC.json
MCSimPython/vessel_data/gunnerus/gunnerus_veres.json
MCSimPython/vessel_data/gunnerus/parV_RVG3DOF.pkl
MCSimPython/vessel_data/gunnerus/parV_RVG6DOF.pkl
MCSimPython/vessel_data/gunnerus/rvg2_config.json
MCSimPython/vessel_data/gunnerus/rvg3ABC_config.json
MCSimPython/vessel_data/gunnerus/rvg3ABC_config_.json
MCSimPython/vessel_data/gunnerus/rvg3_config.json
MCSimPython/vessel_data/gunnerus/rvg_config.json
MCSimPython/vessel_data/gunnerus/vessel.json
MCSimPython/vessel_data/gunnerus/vessel_2.json
MCSimPython/waves/__init__.py
MCSimPython/waves/wave_loads.py
MCSimPython/waves/wave_spectra.py
MCSimPython/waves/wave_spreading.py
MCSimPython-0.1.6.dist-info/LICENSE
MCSimPython-0.1.6.dist-info/METADATA
MCSimPython-0.1.6.dist-info/WHEEL
MCSimPython-0.1.6.dist-info/top_level.txt
MCSimPython-0.1.6.dist-info/RECORD
