Metadata-Version: 2.1
Name: MCSimPython
Version: 0.1.6
Summary: Python vessel simulation environment
Author-email: Jan-Erik Hygen <janereh@stud.ntnu.no>
Keywords: mcsim,MCSimPython,DP,dynamic positioning,Marine Cybernetics
Classifier: Programming Language :: Python :: 3
Classifier: License :: OSI Approved :: GNU General Public License v3 or later (GPLv3+)
Requires-Python: >=3.8
License-File: LICENSE
Requires-Dist: numpy
Requires-Dist: pandas
Requires-Dist: scipy
Requires-Dist: matplotlib
